.DS_Store
pptx2md/__init__.py
pptx2md/__main__.py
pptx2md/global_var.py
pptx2md/outputter.py
pptx2md/parser.py
pptx2md/tools.py
wecode_pptx2md-0.0.1.dist-info/METADATA
wecode_pptx2md-0.0.1.dist-info/WHEEL
wecode_pptx2md-0.0.1.dist-info/entry_points.txt
wecode_pptx2md-0.0.1.dist-info/top_level.txt
wecode_pptx2md-0.0.1.dist-info/RECORD
